fastapi_creation/__init__.py
fastapi_creation/cli.py
fastapi_creation/layouts.py
fastapi_creation/utils.py
fastapi_creation-0.0.6.dist-info/METADATA
fastapi_creation-0.0.6.dist-info/WHEEL
fastapi_creation-0.0.6.dist-info/entry_points.txt
fastapi_creation-0.0.6.dist-info/top_level.txt
fastapi_creation-0.0.6.dist-info/RECORD
